check_reserved_instances/__init__.py
check_reserved_instances/aws.py
check_reserved_instances/calculate.py
check_reserved_instances/config.py
check_reserved_instances/html_template.html
check_reserved_instances/report.py
check_reserved_instances/templates/html_template.html
check_reserved_instances-0.0.10.dist-info/DESCRIPTION.rst
check_reserved_instances-0.0.10.dist-info/METADATA
check_reserved_instances-0.0.10.dist-info/RECORD
check_reserved_instances-0.0.10.dist-info/WHEEL
check_reserved_instances-0.0.10.dist-info/entry_points.txt
check_reserved_instances-0.0.10.dist-info/metadata.json
check_reserved_instances-0.0.10.dist-info/top_level.txt
