Metadata-Version: 2.0
Name: check-reserved-instances
Version: 0.0.10
Summary: Compare instance reservations and running instances for AWS services
Home-page: https://github.com/TerbiumLabs/check-reserved-instances
Author: Terbium Labs
Author-email: developers@terbiumlabs.com
License: BSD
Keywords: ec2 elasticache rds aws reserved instances amazon web services
Platform: Any
Classifier: Development Status :: 5 - Production/Stable
Classifier: Environment :: Console
Classifier: License :: OSI Approved :: BSD License
Classifier: Operating System :: OS Independent
Classifier: Programming Language :: Python
Classifier: Programming Language :: Python :: 2
Classifier: Programming Language :: Python :: 2.7
Classifier: Programming Language :: Python :: 3
Classifier: Programming Language :: Python :: 3.3
Classifier: Programming Language :: Python :: 3.4
Classifier: Programming Language :: Python :: 3.5
Requires-Dist: boto3 (>=1.4.4)
Requires-Dist: click
Requires-Dist: configparser
Requires-Dist: Jinja2
Requires-Dist: MarkupSafe
